{"allowUserKeys":true,"cid":"54","count":0,"deleted":false,"distributeShardsLike":"_graphs","doCompact":true,"id":"54","indexBuckets":8,"indexes":[{"fields":["_key"],"id":"0","selectivityEstimate":1,"sparse":false,"type":"primary","unique":true}],"isSystem":true,"isVolatile":false,"journalSize":1048576,"keyOptions":{"allowUserKeys":true,"type":"traditional"},"name":"_frontend","numberOfShards":1,"planId":"54","replicationFactor":2,"shardKeys":["_key"],"shards":{},"status":0,"type":2,"version":6,"waitForSync":false}
